jkit/__init__.py
jkit/_base.py
jkit/_network_request.py
jkit/_normalization.py
jkit/article.py
jkit/collection.py
jkit/config.py
jkit/constants.py
jkit/credential.py
jkit/exceptions.py
jkit/identifier_check.py
jkit/identifier_convert.py
jkit/jpep/ftn_macket.py
jkit/jpep/platform_settings.py
jkit/lottery.py
jkit/msgspec_constraints.py
jkit/notebook.py
jkit/private/assets.py
jkit/ranking/article_earning.py
jkit/ranking/assets.py
jkit/ranking/daily_update.py
jkit/ranking/user_earning.py
jkit/user.py
jkit-3.0.0a16.dist-info/LICENSE
jkit-3.0.0a16.dist-info/METADATA
jkit-3.0.0a16.dist-info/WHEEL
jkit-3.0.0a16.dist-info/RECORD
