Metadata-Version: 2.1
Name: jkit
Version: 3.0.0a16
Summary: 简书非官方 SDK - 创造可能性
Home-page: https://github.com/FHU-yezi/JKit
License: MIT
Keywords: jianshu,SDK
Author: yezi
Author-email: yehaowei20060411@qq.com
Requires-Python: >=3.8,<4.0
Classifier: Development Status :: 3 - Alpha
Classifier: Framework :: AsyncIO
Classifier: Intended Audience :: Developers
Classifier: License :: OSI Approved :: MIT License
Classifier: Natural Language :: Chinese (Simplified)
Classifier: Programming Language :: Python
Classifier: Programming Language :: Python :: 3
Classifier: Programming Language :: Python :: 3.8
Classifier: Programming Language :: Python :: 3.9
Classifier: Programming Language :: Python :: 3.10
Classifier: Programming Language :: Python :: 3.11
Classifier: Programming Language :: Python :: 3.12
Classifier: Programming Language :: Python :: 3 :: Only
Classifier: Topic :: Software Development :: Libraries
Classifier: Typing :: Typed
Requires-Dist: httpx[http2]
Requires-Dist: msgspec
Requires-Dist: typing-extensions
Project-URL: Repository, https://github.com/FHU-yezi/JKit
